amberdata_rest/__init__.py
amberdata_rest/common.py
amberdata_rest/constants.py
amberdata_rest/utils.py
amberdata_rest/defi/__init__.py
amberdata_rest/defi/service.py
amberdata_rest/examples/__init__.py
amberdata_rest/examples/cex_futures_funding.py
amberdata_rest/examples/cex_futures_long_short_ratio.py
amberdata_rest/examples/cex_futures_open_interest.py
amberdata_rest/examples/cex_spot_price_and_volume.py
amberdata_rest/examples/cex_spot_spot_ohlcv.py
amberdata_rest/examples/cex_spot_trades.py
amberdata_rest/futures/__init__.py
amberdata_rest/futures/service.py
amberdata_rest/spot/__init__.py
amberdata_rest/spot/service.py
amberdata_rest/tests/__init__.py
amberdata_rest/tests/defi/__init__.py
amberdata_rest/tests/defi/test_defi_service.py
amberdata_rest/tests/futures/__init__.py
amberdata_rest/tests/futures/test_futures_service.py
amberdata_rest/tests/spot/__init__.py
amberdata_rest/tests/spot/test_spot_service.py
amberdata_rest-0.3.0.dist-info/LICENSE
amberdata_rest-0.3.0.dist-info/METADATA
amberdata_rest-0.3.0.dist-info/WHEEL
amberdata_rest-0.3.0.dist-info/top_level.txt
amberdata_rest-0.3.0.dist-info/RECORD
