Metadata-Version: 2.1
Name: amberdata_rest
Version: 0.3.0
Summary: Amberdata.io REST API SDK
Author: technology@firestorm.capital
License-File: LICENSE
